<?xml version="1.0" encoding="utf-8"?>
<association id="8a26495d-6328-4e46-aafd-bd35ccd67699">
  <sourceEnd id="425c5582-829e-42bf-85e7-537e334c59ec" type="Call Service Operation Action Source End" typeId="936e090c-8408-429d-b2f6-2eb8deecc428">
    <display>: CreateCustomer</display>
    <order>0</order>
    <typeReference id="acb45dc2-e76c-4c09-b3e0-cdc9cf8604a1">
      <typeId>a782a208-aec3-4314-94f9-522f81574c6f</typeId>
      <isNavigable>false</isNavigable>
      <isNullable>false</isNullable>
      <isCollection>false</isCollection>
      <isRequired>true</isRequired>
      <typePackageName>Intent.Sample.Angular.UI</typePackageName>
      <typePackageId>057de13e-cf1a-41aa-914f-f88d95e463f4</typePackageId>
      <stereotypes />
      <genericTypeParameters />
    </typeReference>
    <stereotypes />
    <metadata />
    <childElements />
  </sourceEnd>
  <targetEnd id="8a26495d-6328-4e46-aafd-bd35ccd67699" type="Call Service Operation Action Target End" typeId="475f0810-2b4a-40da-8eb8-697cb62f7dbe">
    <name>CreateCustomerCommand</name>
    <display>[call] Customers.CreateCustomerCommand: guid</display>
    <order>0</order>
    <traits>
      <trait id="dc813928-0ce1-4f66-ae31-b5e5d506b4a3" name="[Invokable]" />
    </traits>
    <typeReference id="0abdfea4-a995-45a3-afd0-97a5dda02460">
      <typeId>75d1c4b7-275f-4db7-b5ac-eb0c384e27e3</typeId>
      <isNavigable>true</isNavigable>
      <isNullable>false</isNullable>
      <isCollection>false</isCollection>
      <isRequired>true</isRequired>
      <typePackageName>Intent.Sample.Angular.Backend.Services</typePackageName>
      <typePackageId>518ad6a2-953d-4588-95e4-35ba4905dc7b</typePackageId>
      <stereotypes />
      <genericTypeParameters />
    </typeReference>
    <stereotypes />
    <mappings>
      <mapping type="Call Service Mapping" typeId="e4a4111b-cf13-4efe-8a5d-fea9457ac8ad">
        <source applicationId="9984788e-6d43-4e13-9121-d43d720222af" designerId="f492faed-0665-4513-9853-5a230721786f" elementId="7ba013f6-f7a7-465f-890b-57b5c7833066" location="[Intent.Sample.Angular].[User Interface].[CustomerAddPage]" />
        <target applicationId="4f799450-9dd9-4f4c-9740-262eafcfa4da" designerId="81104ae6-2bc5-4bae-b05a-f987b0372d81" elementId="75d1c4b7-275f-4db7-b5ac-eb0c384e27e3" location="[Intent.Sample.Angular].[User Interface].[CreateCustomerCommand]" />
        <mappedEnds>
          <mappedEnd>
            <expression>{CreateCustomer.CreateCustomerCommand}</expression>
            <path>
              <target id="75d1c4b7-275f-4db7-b5ac-eb0c384e27e3" name="CreateCustomerCommand" type="element" specialization="Command" specializationId="ccf14eb6-3a55-4d81-b5b9-d27311c70cb9" />
            </path>
            <sources>
              <source identifier="CreateCustomer.CreateCustomerCommand" mappingType="Invocation Mapping" mappingTypeId="ab447316-1252-49bc-a695-f34cb00a3cdc">
                <path>
                  <target id="7ba013f6-f7a7-465f-890b-57b5c7833066" name="CustomerAddPage" type="element" specialization="Component" specializationId="b1c481e1-e91e-4c29-9817-00ab9cad4b6b" />
                  <target id="a782a208-aec3-4314-94f9-522f81574c6f" name="CreateCustomer" type="element" specialization="Component Operation" specializationId="e030c97a-e066-40a7-8188-808c275df3cb" />
                  <target id="8a26495d-6328-4e46-aafd-bd35ccd67699" name="CreateCustomerCommand" type="association" specialization="Call Service Operation Action Target End" specializationId="475f0810-2b4a-40da-8eb8-697cb62f7dbe" />
                </path>
              </source>
            </sources>
          </mappedEnd>
          <mappedEnd>
            <expression>{Model.TitleId}</expression>
            <path>
              <target id="75d1c4b7-275f-4db7-b5ac-eb0c384e27e3" name="CreateCustomerCommand" type="element" specialization="Command" specializationId="ccf14eb6-3a55-4d81-b5b9-d27311c70cb9" />
              <target id="83f612da-05fd-46d3-b8dc-5c9d57aac306" name="TitleId" type="element" specialization="DTO-Field" specializationId="7baed1fd-469b-4980-8fd9-4cefb8331eb2" />
            </path>
            <sources>
              <source identifier="Model.TitleId" mappingType="Data Mapping" mappingTypeId="ce70308a-e29d-4644-8410-f9e6bbd214fc">
                <path>
                  <target id="7ba013f6-f7a7-465f-890b-57b5c7833066" name="CustomerAddPage" type="element" specialization="Component" specializationId="b1c481e1-e91e-4c29-9817-00ab9cad4b6b" />
                  <target id="90684108-b182-4bb2-8574-a3a8a3383aa1" name="Model" type="element" specialization="Property" specializationId="356fbe17-bc63-4e16-b915-feefbc063cbe" />
                  <target id="50006e67-536a-458d-a141-427e90c03d2f" name="TitleId" type="element" specialization="Property" specializationId="356fbe17-bc63-4e16-b915-feefbc063cbe" />
                </path>
              </source>
            </sources>
          </mappedEnd>
          <mappedEnd>
            <expression>{Model.Name}</expression>
            <path>
              <target id="75d1c4b7-275f-4db7-b5ac-eb0c384e27e3" name="CreateCustomerCommand" type="element" specialization="Command" specializationId="ccf14eb6-3a55-4d81-b5b9-d27311c70cb9" />
              <target id="3f15a4e5-a63f-408c-a5a4-c79587780faf" name="Name" type="element" specialization="DTO-Field" specializationId="7baed1fd-469b-4980-8fd9-4cefb8331eb2" />
            </path>
            <sources>
              <source identifier="Model.Name" mappingType="Data Mapping" mappingTypeId="ce70308a-e29d-4644-8410-f9e6bbd214fc">
                <path>
                  <target id="7ba013f6-f7a7-465f-890b-57b5c7833066" name="CustomerAddPage" type="element" specialization="Component" specializationId="b1c481e1-e91e-4c29-9817-00ab9cad4b6b" />
                  <target id="90684108-b182-4bb2-8574-a3a8a3383aa1" name="Model" type="element" specialization="Property" specializationId="356fbe17-bc63-4e16-b915-feefbc063cbe" />
                  <target id="9c3d43fd-e9ed-4cdd-a761-9cf56879f772" name="Name" type="element" specialization="Property" specializationId="356fbe17-bc63-4e16-b915-feefbc063cbe" />
                </path>
              </source>
            </sources>
          </mappedEnd>
          <mappedEnd>
            <expression>{Model.Surname}</expression>
            <path>
              <target id="75d1c4b7-275f-4db7-b5ac-eb0c384e27e3" name="CreateCustomerCommand" type="element" specialization="Command" specializationId="ccf14eb6-3a55-4d81-b5b9-d27311c70cb9" />
              <target id="b26eff7e-f92e-43c5-97e8-efb50c020b4d" name="Surname" type="element" specialization="DTO-Field" specializationId="7baed1fd-469b-4980-8fd9-4cefb8331eb2" />
            </path>
            <sources>
              <source identifier="Model.Surname" mappingType="Data Mapping" mappingTypeId="ce70308a-e29d-4644-8410-f9e6bbd214fc">
                <path>
                  <target id="7ba013f6-f7a7-465f-890b-57b5c7833066" name="CustomerAddPage" type="element" specialization="Component" specializationId="b1c481e1-e91e-4c29-9817-00ab9cad4b6b" />
                  <target id="90684108-b182-4bb2-8574-a3a8a3383aa1" name="Model" type="element" specialization="Property" specializationId="356fbe17-bc63-4e16-b915-feefbc063cbe" />
                  <target id="cfb5d2b4-9859-4dcc-b349-cdcac42881ef" name="Surname" type="element" specialization="Property" specializationId="356fbe17-bc63-4e16-b915-feefbc063cbe" />
                </path>
              </source>
            </sources>
          </mappedEnd>
          <mappedEnd>
            <expression>{Model.Email}</expression>
            <path>
              <target id="75d1c4b7-275f-4db7-b5ac-eb0c384e27e3" name="CreateCustomerCommand" type="element" specialization="Command" specializationId="ccf14eb6-3a55-4d81-b5b9-d27311c70cb9" />
              <target id="eee3fc0d-631a-4bab-b503-dd5209f9bab7" name="Email" type="element" specialization="DTO-Field" specializationId="7baed1fd-469b-4980-8fd9-4cefb8331eb2" />
            </path>
            <sources>
              <source identifier="Model.Email" mappingType="Data Mapping" mappingTypeId="ce70308a-e29d-4644-8410-f9e6bbd214fc">
                <path>
                  <target id="7ba013f6-f7a7-465f-890b-57b5c7833066" name="CustomerAddPage" type="element" specialization="Component" specializationId="b1c481e1-e91e-4c29-9817-00ab9cad4b6b" />
                  <target id="90684108-b182-4bb2-8574-a3a8a3383aa1" name="Model" type="element" specialization="Property" specializationId="356fbe17-bc63-4e16-b915-feefbc063cbe" />
                  <target id="3be66f06-ccb8-4d4d-b297-5d8ba2ebb6eb" name="Email" type="element" specialization="Property" specializationId="356fbe17-bc63-4e16-b915-feefbc063cbe" />
                </path>
              </source>
            </sources>
          </mappedEnd>
          <mappedEnd>
            <expression>{Model.IsActive}</expression>
            <path>
              <target id="75d1c4b7-275f-4db7-b5ac-eb0c384e27e3" name="CreateCustomerCommand" type="element" specialization="Command" specializationId="ccf14eb6-3a55-4d81-b5b9-d27311c70cb9" />
              <target id="8d2e56ca-2130-4457-8f64-de9ac4111dc5" name="IsActive" type="element" specialization="DTO-Field" specializationId="7baed1fd-469b-4980-8fd9-4cefb8331eb2" />
            </path>
            <sources>
              <source identifier="Model.IsActive" mappingType="Data Mapping" mappingTypeId="ce70308a-e29d-4644-8410-f9e6bbd214fc">
                <path>
                  <target id="7ba013f6-f7a7-465f-890b-57b5c7833066" name="CustomerAddPage" type="element" specialization="Component" specializationId="b1c481e1-e91e-4c29-9817-00ab9cad4b6b" />
                  <target id="90684108-b182-4bb2-8574-a3a8a3383aa1" name="Model" type="element" specialization="Property" specializationId="356fbe17-bc63-4e16-b915-feefbc063cbe" />
                  <target id="659390ab-567b-4d86-9644-5788eea6ac5f" name="IsActive" type="element" specialization="Property" specializationId="356fbe17-bc63-4e16-b915-feefbc063cbe" />
                </path>
              </source>
            </sources>
          </mappedEnd>
          <mappedEnd>
            <expression>{Model.Addresses}</expression>
            <path>
              <target id="75d1c4b7-275f-4db7-b5ac-eb0c384e27e3" name="CreateCustomerCommand" type="element" specialization="Command" specializationId="ccf14eb6-3a55-4d81-b5b9-d27311c70cb9" />
              <target id="969ae598-6044-4327-92ec-5e5c753c846a" name="Addresses" type="element" specialization="DTO-Field" specializationId="7baed1fd-469b-4980-8fd9-4cefb8331eb2" />
            </path>
            <sources>
              <source identifier="Model.Addresses" mappingType="Data Mapping" mappingTypeId="ce70308a-e29d-4644-8410-f9e6bbd214fc">
                <path>
                  <target id="7ba013f6-f7a7-465f-890b-57b5c7833066" name="CustomerAddPage" type="element" specialization="Component" specializationId="b1c481e1-e91e-4c29-9817-00ab9cad4b6b" />
                  <target id="90684108-b182-4bb2-8574-a3a8a3383aa1" name="Model" type="element" specialization="Property" specializationId="356fbe17-bc63-4e16-b915-feefbc063cbe" />
                  <target id="1bf61671-4efc-4b5f-875d-baf1225fde2a" name="Addresses" type="element" specialization="Property" specializationId="356fbe17-bc63-4e16-b915-feefbc063cbe" />
                </path>
              </source>
            </sources>
          </mappedEnd>
          <mappedEnd>
            <expression>{Model.Addresses.Line1}</expression>
            <path>
              <target id="75d1c4b7-275f-4db7-b5ac-eb0c384e27e3" name="CreateCustomerCommand" type="element" specialization="Command" specializationId="ccf14eb6-3a55-4d81-b5b9-d27311c70cb9" />
              <target id="969ae598-6044-4327-92ec-5e5c753c846a" name="Addresses" type="element" specialization="DTO-Field" specializationId="7baed1fd-469b-4980-8fd9-4cefb8331eb2" />
              <target id="7be82036-7b66-44eb-bfa1-255fe4384037" name="Line1" type="element" specialization="DTO-Field" specializationId="7baed1fd-469b-4980-8fd9-4cefb8331eb2" />
            </path>
            <sources>
              <source identifier="Model.Addresses.Line1" mappingType="Data Mapping" mappingTypeId="ce70308a-e29d-4644-8410-f9e6bbd214fc">
                <path>
                  <target id="7ba013f6-f7a7-465f-890b-57b5c7833066" name="CustomerAddPage" type="element" specialization="Component" specializationId="b1c481e1-e91e-4c29-9817-00ab9cad4b6b" />
                  <target id="90684108-b182-4bb2-8574-a3a8a3383aa1" name="Model" type="element" specialization="Property" specializationId="356fbe17-bc63-4e16-b915-feefbc063cbe" />
                  <target id="1bf61671-4efc-4b5f-875d-baf1225fde2a" name="Addresses" type="element" specialization="Property" specializationId="356fbe17-bc63-4e16-b915-feefbc063cbe" />
                  <target id="ad0ee05f-f948-4d3a-a574-ccc66bf3fd62" name="Line1" type="element" specialization="Property" specializationId="356fbe17-bc63-4e16-b915-feefbc063cbe" />
                </path>
              </source>
            </sources>
          </mappedEnd>
          <mappedEnd>
            <expression>{Model.Addresses.Line2}</expression>
            <path>
              <target id="75d1c4b7-275f-4db7-b5ac-eb0c384e27e3" name="CreateCustomerCommand" type="element" specialization="Command" specializationId="ccf14eb6-3a55-4d81-b5b9-d27311c70cb9" />
              <target id="969ae598-6044-4327-92ec-5e5c753c846a" name="Addresses" type="element" specialization="DTO-Field" specializationId="7baed1fd-469b-4980-8fd9-4cefb8331eb2" />
              <target id="16196d38-bff6-4756-8621-12ae84ad9f37" name="Line2" type="element" specialization="DTO-Field" specializationId="7baed1fd-469b-4980-8fd9-4cefb8331eb2" />
            </path>
            <sources>
              <source identifier="Model.Addresses.Line2" mappingType="Data Mapping" mappingTypeId="ce70308a-e29d-4644-8410-f9e6bbd214fc">
                <path>
                  <target id="7ba013f6-f7a7-465f-890b-57b5c7833066" name="CustomerAddPage" type="element" specialization="Component" specializationId="b1c481e1-e91e-4c29-9817-00ab9cad4b6b" />
                  <target id="90684108-b182-4bb2-8574-a3a8a3383aa1" name="Model" type="element" specialization="Property" specializationId="356fbe17-bc63-4e16-b915-feefbc063cbe" />
                  <target id="1bf61671-4efc-4b5f-875d-baf1225fde2a" name="Addresses" type="element" specialization="Property" specializationId="356fbe17-bc63-4e16-b915-feefbc063cbe" />
                  <target id="f62bfe50-d881-45c6-b42a-881c05db1ec7" name="Line2" type="element" specialization="Property" specializationId="356fbe17-bc63-4e16-b915-feefbc063cbe" />
                </path>
              </source>
            </sources>
          </mappedEnd>
          <mappedEnd>
            <expression>{Model.Addresses.City}</expression>
            <path>
              <target id="75d1c4b7-275f-4db7-b5ac-eb0c384e27e3" name="CreateCustomerCommand" type="element" specialization="Command" specializationId="ccf14eb6-3a55-4d81-b5b9-d27311c70cb9" />
              <target id="969ae598-6044-4327-92ec-5e5c753c846a" name="Addresses" type="element" specialization="DTO-Field" specializationId="7baed1fd-469b-4980-8fd9-4cefb8331eb2" />
              <target id="a275c12a-27c5-42f5-a869-3938ddf699c3" name="City" type="element" specialization="DTO-Field" specializationId="7baed1fd-469b-4980-8fd9-4cefb8331eb2" />
            </path>
            <sources>
              <source identifier="Model.Addresses.City" mappingType="Data Mapping" mappingTypeId="ce70308a-e29d-4644-8410-f9e6bbd214fc">
                <path>
                  <target id="7ba013f6-f7a7-465f-890b-57b5c7833066" name="CustomerAddPage" type="element" specialization="Component" specializationId="b1c481e1-e91e-4c29-9817-00ab9cad4b6b" />
                  <target id="90684108-b182-4bb2-8574-a3a8a3383aa1" name="Model" type="element" specialization="Property" specializationId="356fbe17-bc63-4e16-b915-feefbc063cbe" />
                  <target id="1bf61671-4efc-4b5f-875d-baf1225fde2a" name="Addresses" type="element" specialization="Property" specializationId="356fbe17-bc63-4e16-b915-feefbc063cbe" />
                  <target id="cbbfec41-ed42-4e98-88a8-17861aeb7c8b" name="City" type="element" specialization="Property" specializationId="356fbe17-bc63-4e16-b915-feefbc063cbe" />
                </path>
              </source>
            </sources>
          </mappedEnd>
          <mappedEnd>
            <expression>{Model.Addresses.Postal}</expression>
            <path>
              <target id="75d1c4b7-275f-4db7-b5ac-eb0c384e27e3" name="CreateCustomerCommand" type="element" specialization="Command" specializationId="ccf14eb6-3a55-4d81-b5b9-d27311c70cb9" />
              <target id="969ae598-6044-4327-92ec-5e5c753c846a" name="Addresses" type="element" specialization="DTO-Field" specializationId="7baed1fd-469b-4980-8fd9-4cefb8331eb2" />
              <target id="4e16f087-4d7c-47d3-b86e-069b021c4ce9" name="Postal" type="element" specialization="DTO-Field" specializationId="7baed1fd-469b-4980-8fd9-4cefb8331eb2" />
            </path>
            <sources>
              <source identifier="Model.Addresses.Postal" mappingType="Data Mapping" mappingTypeId="ce70308a-e29d-4644-8410-f9e6bbd214fc">
                <path>
                  <target id="7ba013f6-f7a7-465f-890b-57b5c7833066" name="CustomerAddPage" type="element" specialization="Component" specializationId="b1c481e1-e91e-4c29-9817-00ab9cad4b6b" />
                  <target id="90684108-b182-4bb2-8574-a3a8a3383aa1" name="Model" type="element" specialization="Property" specializationId="356fbe17-bc63-4e16-b915-feefbc063cbe" />
                  <target id="1bf61671-4efc-4b5f-875d-baf1225fde2a" name="Addresses" type="element" specialization="Property" specializationId="356fbe17-bc63-4e16-b915-feefbc063cbe" />
                  <target id="ef2202ee-4624-441b-bf6c-5096fffb6167" name="Postal" type="element" specialization="Property" specializationId="356fbe17-bc63-4e16-b915-feefbc063cbe" />
                </path>
              </source>
            </sources>
          </mappedEnd>
          <mappedEnd>
            <expression>{Model.Addresses.AddressType}</expression>
            <path>
              <target id="75d1c4b7-275f-4db7-b5ac-eb0c384e27e3" name="CreateCustomerCommand" type="element" specialization="Command" specializationId="ccf14eb6-3a55-4d81-b5b9-d27311c70cb9" />
              <target id="969ae598-6044-4327-92ec-5e5c753c846a" name="Addresses" type="element" specialization="DTO-Field" specializationId="7baed1fd-469b-4980-8fd9-4cefb8331eb2" />
              <target id="e7f1548b-594d-48e2-a22b-4f331d2d5186" name="AddressType" type="element" specialization="DTO-Field" specializationId="7baed1fd-469b-4980-8fd9-4cefb8331eb2" />
            </path>
            <sources>
              <source identifier="Model.Addresses.AddressType" mappingType="Data Mapping" mappingTypeId="ce70308a-e29d-4644-8410-f9e6bbd214fc">
                <path>
                  <target id="7ba013f6-f7a7-465f-890b-57b5c7833066" name="CustomerAddPage" type="element" specialization="Component" specializationId="b1c481e1-e91e-4c29-9817-00ab9cad4b6b" />
                  <target id="90684108-b182-4bb2-8574-a3a8a3383aa1" name="Model" type="element" specialization="Property" specializationId="356fbe17-bc63-4e16-b915-feefbc063cbe" />
                  <target id="1bf61671-4efc-4b5f-875d-baf1225fde2a" name="Addresses" type="element" specialization="Property" specializationId="356fbe17-bc63-4e16-b915-feefbc063cbe" />
                  <target id="8985517d-ac55-400e-aa62-127f2e7b915d" name="AddressType" type="element" specialization="Property" specializationId="356fbe17-bc63-4e16-b915-feefbc063cbe" />
                </path>
              </source>
            </sources>
          </mappedEnd>
          <mappedEnd>
            <expression>{Model.Loyalty.LoyaltyNo}</expression>
            <path>
              <target id="75d1c4b7-275f-4db7-b5ac-eb0c384e27e3" name="CreateCustomerCommand" type="element" specialization="Command" specializationId="ccf14eb6-3a55-4d81-b5b9-d27311c70cb9" />
              <target id="a95d2c3e-5e13-442a-901e-4a3b9f610d4e" name="Loyalty" type="element" specialization="DTO-Field" specializationId="7baed1fd-469b-4980-8fd9-4cefb8331eb2" />
              <target id="88c1da36-1f10-46ff-9ed1-12dd0219f2f5" name="LoyaltyNo" type="element" specialization="DTO-Field" specializationId="7baed1fd-469b-4980-8fd9-4cefb8331eb2" />
            </path>
            <sources>
              <source identifier="Model.Loyalty.LoyaltyNo" mappingType="Data Mapping" mappingTypeId="ce70308a-e29d-4644-8410-f9e6bbd214fc">
                <path>
                  <target id="7ba013f6-f7a7-465f-890b-57b5c7833066" name="CustomerAddPage" type="element" specialization="Component" specializationId="b1c481e1-e91e-4c29-9817-00ab9cad4b6b" />
                  <target id="90684108-b182-4bb2-8574-a3a8a3383aa1" name="Model" type="element" specialization="Property" specializationId="356fbe17-bc63-4e16-b915-feefbc063cbe" />
                  <target id="230b4f6b-7004-4469-ab44-f125345119bf" name="Loyalty" type="element" specialization="Property" specializationId="356fbe17-bc63-4e16-b915-feefbc063cbe" />
                  <target id="d5768511-ff91-475c-8238-4766dd757e50" name="LoyaltyNo" type="element" specialization="Property" specializationId="356fbe17-bc63-4e16-b915-feefbc063cbe" />
                </path>
              </source>
            </sources>
          </mappedEnd>
          <mappedEnd>
            <expression>{Model.Loyalty.Points}</expression>
            <path>
              <target id="75d1c4b7-275f-4db7-b5ac-eb0c384e27e3" name="CreateCustomerCommand" type="element" specialization="Command" specializationId="ccf14eb6-3a55-4d81-b5b9-d27311c70cb9" />
              <target id="a95d2c3e-5e13-442a-901e-4a3b9f610d4e" name="Loyalty" type="element" specialization="DTO-Field" specializationId="7baed1fd-469b-4980-8fd9-4cefb8331eb2" />
              <target id="e4c2c01e-082a-44df-8383-9cd58d4ceeb0" name="Points" type="element" specialization="DTO-Field" specializationId="7baed1fd-469b-4980-8fd9-4cefb8331eb2" />
            </path>
            <sources>
              <source identifier="Model.Loyalty.Points" mappingType="Data Mapping" mappingTypeId="ce70308a-e29d-4644-8410-f9e6bbd214fc">
                <path>
                  <target id="7ba013f6-f7a7-465f-890b-57b5c7833066" name="CustomerAddPage" type="element" specialization="Component" specializationId="b1c481e1-e91e-4c29-9817-00ab9cad4b6b" />
                  <target id="90684108-b182-4bb2-8574-a3a8a3383aa1" name="Model" type="element" specialization="Property" specializationId="356fbe17-bc63-4e16-b915-feefbc063cbe" />
                  <target id="230b4f6b-7004-4469-ab44-f125345119bf" name="Loyalty" type="element" specialization="Property" specializationId="356fbe17-bc63-4e16-b915-feefbc063cbe" />
                  <target id="8ccbe901-7111-4f17-97c5-6687d8aa5f25" name="Points" type="element" specialization="Property" specializationId="356fbe17-bc63-4e16-b915-feefbc063cbe" />
                </path>
              </source>
            </sources>
          </mappedEnd>
        </mappedEnds>
      </mapping>
    </mappings>
    <metadata />
    <childElements />
  </targetEnd>
  <associationType>Call Service Operation Action</associationType>
  <associationTypeId>fe5a5cd8-aabd-472f-8d42-f5c233e658dc</associationTypeId>
  <stereotypes />
</association>