<?xml version="1.0" encoding="utf-8"?>
<class id="dfc5856c-d689-45a8-b314-48c546bab9cb" type="Component View" typeId="624513a6-cba8-4dde-8ebe-6b19f00f0364">
  <name>[view]</name>
  <display>[view]</display>
  <isAbstract>false</isAbstract>
  <order>0</order>
  <genericTypes />
  <isMapped>false</isMapped>
  <parentFolderId>91998985-b788-4232-ab8e-19eb2c8b5355</parentFolderId>
  <packageId>352d33f1-2157-4a2e-9fd8-3235ca46b372</packageId>
  <packageName>eShop.Web.UI</packageName>
  <stereotypes />
  <metadata />
  <childElements />
</class>